[
  {
    "id": 99,
    "rank": 1,
    "adult": 0,
    "title": "All About My Mother",
    "tvdbid": null,
    "imdb_id": null,
    "mediatype": "movie",
    "release_year": 1999
  },
  {
    "id": 64,
    "rank": 2,
    "adult": 0,
    "title": "Talk to Her",
    "tvdbid": null,
    "imdb_id": null,
    "mediatype": "movie",
    "release_year": 2002
  },
  {
    "id": 219,
    "rank": 3,
    "adult": 0,
    "title": "Volver",
    "tvdbid": null,
    "imdb_id": null,
    "mediatype": "movie",
    "release_year": 2006
  },
  {
    "id": 519010,
    "rank": 4,
    "adult": 0,
    "title": "Pain and Glory",
    "tvdbid": null,
    "imdb_id": null,
    "mediatype": "movie",
    "release_year": 2019
  },
  {
    "id": 63311,
    "rank": 5,
    "adult": 0,
    "title": "The Skin I Live In",
    "tvdbid": null,
    "imdb_id": null,
    "mediatype": "movie",
    "release_year": 2011
  },
  {
    "id": 766798,
    "rank": 6,
    "adult": 0,
    "title": "Parallel Mothers",
    "tvdbid": null,
    "imdb_id": null,
    "mediatype": "movie",
    "release_year": 2021
  },
  {
    "id": 4203,
    "rank": 7,
    "adult": 0,
    "title": "Women on the Verge of a Nervous Breakdown",
    "tvdbid": null,
    "imdb_id": null,
    "mediatype": "movie",
    "release_year": 1988
  },
  {
    "id": 140,
    "rank": 8,
    "adult": 0,
    "title": "Bad Education",
    "tvdbid": null,
    "imdb_id": null,
    "mediatype": "movie",
    "release_year": 2004
  },
  {
    "id": 332872,
    "rank": 9,
    "adult": 0,
    "title": "Julieta",
    "tvdbid": null,
    "imdb_id": null,
    "mediatype": "movie",
    "release_year": 2016
  },
  {
    "id": 4307,
    "rank": 10,
    "adult": 0,
    "title": "The Flower of My Secret",
    "tvdbid": null,
    "imdb_id": null,
    "mediatype": "movie",
    "release_year": 1995
  },
  {
    "id": 2469,
    "rank": 11,
    "adult": 0,
    "title": "Tie Me Up! Tie Me Down!",
    "tvdbid": null,
    "imdb_id": null,
    "mediatype": "movie",
    "release_year": 1989
  },
  {
    "id": 4043,
    "rank": 12,
    "adult": 0,
    "title": "Law of Desire",
    "tvdbid": null,
    "imdb_id": null,
    "mediatype": "movie",
    "release_year": 1987
  },
  {
    "id": 8221,
    "rank": 13,
    "adult": 0,
    "title": "What Have I Done to Deserve This?",
    "tvdbid": null,
    "imdb_id": null,
    "mediatype": "movie",
    "release_year": 1984
  }
]